legisweb_api-0.0.5.dist-info/licenses/LICENSE
legiswebapi/__init__.py
legiswebapi/legisweb_client.py
legisweb_api-0.0.5.dist-info/METADATA
legisweb_api-0.0.5.dist-info/WHEEL
legisweb_api-0.0.5.dist-info/top_level.txt
legisweb_api-0.0.5.dist-info/RECORD
