Metadata-Version: 2.4
Name: legisweb-api
Version: 0.0.5
Summary: Cliente Python para a API Legisweb
Home-page: https://github.com/ismaelnjr/legisweb-api-project
Author: Ismael Nascimento
Author-email: ismaelnjr@icloud.com
Classifier: Programming Language :: Python :: 3
Classifier: License :: OSI Approved :: MIT License
Classifier: Operating System :: OS Independent
Requires-Python: >=3.7
License-File: LICENSE
Requires-Dist: requests
Dynamic: author
Dynamic: author-email
Dynamic: classifier
Dynamic: description
Dynamic: description-content-type
Dynamic: home-page
Dynamic: license-file
Dynamic: requires-dist
Dynamic: requires-python
Dynamic: summary
